MANIFEST.in
README.rst
pack.py
setup.cfg
setup.py
BrainpyLib/BrainpyBase.pyc
BrainpyLib/Common.pyc
BrainpyLib/__init__.py
BrainpyLib/lb1_SNN.pyc
BrainpyLib/lb2_SNN.pyc
BrainpyLib/lb2_checkRes.pyc
BrainpyLib/lb2_deploy.pyc
BrainpyLib/__pycache__/BrainpyBase.cpython-310.pyc
BrainpyLib/__pycache__/Common.cpython-310.pyc
BrainpyLib/__pycache__/lb2_SNN.cpython-310.pyc
BrainpyLib/__pycache__/lb2_checkRes.cpython-310.pyc
BrainpyLib/__pycache__/lb2_deploy.cpython-310.pyc
Gdiist_BPU_Toolkit.egg-info/PKG-INFO
Gdiist_BPU_Toolkit.egg-info/SOURCES.txt
Gdiist_BPU_Toolkit.egg-info/dependency_links.txt
Gdiist_BPU_Toolkit.egg-info/requires.txt
Gdiist_BPU_Toolkit.egg-info/top_level.txt
GraphLib/Graph28nm.pyc
GraphLib/GraphBase.pyc
GraphLib/GraphGen.pyc
GraphLib/__init__.py
GraphLib/cora_demo.pyc
GraphLib/gcn_weight.pyc
GraphLib/karate_demo.pyc
GraphLib/lb2_GCN.pyc
GraphLib/lb2_Graph.pyc
HardwareConfig/__init__.py
Mapping/Router.pyc
Mapping/W2H.pyc
Mapping/__init__.py
Mapping/lb1_weight.pyc
Mapping/lb2_weight.pyc
Mapping/__pycache__/Router.cpython-310.pyc
Mapping/__pycache__/W2H.cpython-310.pyc
Mapping/__pycache__/__init__.cpython-310.pyc
Mapping/__pycache__/lb2_weight.cpython-310.pyc
Models/EImodel.py
Models/EImodel_Izhikevich.py
Models/EImodel_new.py
Models/EImodel_new_complex.py
Models/EImodel_new_lb2.py
Models/EImodel_new_lb2_int8.py
Models/Emodel_legancy.py
Models/__init__.py
Models/neuron4EIModel.py
Models/__pycache__/EImodel_new_lb2.cpython-310.pyc
Models/__pycache__/__init__.cpython-310.pyc
SNNCompiler/SMT_Base.pyc
SNNCompiler/__init__.py
SNNCompiler/lb1_Compiler.pyc
SNNCompiler/lb2_Compiler.pyc
SNNCompiler/__pycache__/__init__.cpython-310.pyc
SNNCompiler/__pycache__/lb2_Compiler.cpython-310.pyc
SNNCompiler/snn_compiler_32bit/__init__.pyc
SNNCompiler/snn_compiler_32bit/fun2smt_32bit.pyc
SNNCompiler/snn_compiler_32bit/backend/__init__.pyc
SNNCompiler/snn_compiler_32bit/backend/smt.pyc
SNNCompiler/snn_compiler_32bit/backend/smt_factory.pyc
SNNCompiler/snn_compiler_32bit/common/__init__.pyc
SNNCompiler/snn_compiler_32bit/common/operator.pyc
SNNCompiler/snn_compiler_32bit/common/register.pyc
SNNCompiler/snn_compiler_32bit/common/register_collection.pyc
