Metadata-Version: 2.1
Name: Gdiist-BPU-Toolkit
Version: 0.2
Author: GDIIST
Author-email: 739503445@qq.com
License: MIT
Requires-Dist: brainpy>=2.4.2
